covidata/__init__.py
covidata/esa/__init__.py
covidata/esa/mortality_natality.py
covidata/esa/opendata.py
covidata/jaxa/__init__.py
covidata/jaxa/gosat.py
covidata/nasa/__init__.py
covidata/nasa/atmospheric.py
covidata/nasa/earthdata_login.py
covidata/nasa/landslide.py
covidata-0.0.6.dist-info/LICENSE
covidata-0.0.6.dist-info/METADATA
covidata-0.0.6.dist-info/WHEEL
covidata-0.0.6.dist-info/top_level.txt
covidata-0.0.6.dist-info/RECORD
