Metadata-Version: 2.1
Name: covidata
Version: 0.0.6
Summary: Easily access NASA, ESA and JAXA data
Home-page: https://github.com/lusmoura/Nasa-space-apps
Author: Control-space
Author-email: author@example.com
License: UNKNOWN
Platform: UNKNOWN
Classifier: Programming Language :: Python :: 3
Classifier: License :: OSI Approved :: MIT License
Classifier: Operating System :: OS Independent
Requires-Python: >=3.6
Requires-Dist: pandas
Requires-Dist: requests
Requires-Dist: beautifulsoup4
Requires-Dist: lxml
